rankseg/__init__.py
rankseg/_rankseg.py
rankseg/_rankseg_algo.py
rankseg/distribution.py
rankseg-0.0.3.dist-info/licenses/LICENSE
rankseg-0.0.3.dist-info/METADATA
rankseg-0.0.3.dist-info/WHEEL
rankseg-0.0.3.dist-info/top_level.txt
rankseg-0.0.3.dist-info/RECORD
