Metadata-Version: 2.4
Name: rankseg
Version: 0.0.3
Summary: RankSEG: A Statistically Consistent Segmentation Prediction Solver for Dice and IoU Metrics Optimization
Home-page: https://rankseg.readthedocs.io/en/latest/
Author: ['Ben Dai', 'Zixun Wang']
Author-email: bendai@cuhk.edu.hk
Project-URL: Documentation, https://rankseg.readthedocs.io/en/latest/
Project-URL: Source, https://github.com/rankseg/rankseg
Project-URL: Tracker, https://github.com/rankseg/rankseg/issues
Keywords: segmentation,deep-learning,pytorch,computer-vision,dice-loss,iou,rankseg
Classifier: Development Status :: 4 - Beta
Classifier: Intended Audience :: Science/Research
Classifier: Intended Audience :: Developers
Classifier: Topic :: Scientific/Engineering :: Artificial Intelligence
Classifier: License :: OSI Approved :: BSD License
Classifier: Programming Language :: Python :: 3
Classifier: Programming Language :: Python :: 3.9
Classifier: Programming Language :: Python :: 3.10
Classifier: Programming Language :: Python :: 3.11
Classifier: Operating System :: OS Independent
Requires-Python: >= 3.9
License-File: LICENSE
Requires-Dist: torch
Requires-Dist: scipy
Requires-Dist: numpy
Dynamic: author
Dynamic: author-email
Dynamic: classifier
Dynamic: description
Dynamic: description-content-type
Dynamic: home-page
Dynamic: keywords
Dynamic: license-file
Dynamic: project-url
Dynamic: requires-dist
Dynamic: requires-python
Dynamic: summary
